{
  "name": "Selvadentro API Gateway",
  "nodes": [
    {
      "parameters": {
        "httpMethod": "GET",
        "path": "selvadentro",
        "responseMode": "responseNode"
      },
      "id": "webhook-trigger",
      "name": "Webhook",
      "type": "n8n-nodes-base.webhook",
      "typeVersion": 1,
      "position": [250, 300]
    },
    {
      "parameters": {
        "conditions": {
          "string": [
            {
              "value1": "={{ $json.query.endpoint }}",
              "operation": "equals",
              "value2": "metrics"
            }
          ]
        }
      },
      "id": "if-metrics",
      "name": "IF Metrics",
      "type": "n8n-nodes-base.if",
      "typeVersion": 1,
      "position": [450, 100]
    },
    {
      "parameters": {
        "conditions": {
          "string": [
            {
              "value1": "={{ $json.query.endpoint }}",
              "operation": "equals",
              "value2": "pipeline"
            }
          ]
        }
      },
      "id": "if-pipeline",
      "name": "IF Pipeline",
      "type": "n8n-nodes-base.if",
      "typeVersion": 1,
      "position": [450, 200]
    },
    {
      "parameters": {
        "conditions": {
          "string": [
            {
              "value1": "={{ $json.query.endpoint }}",
              "operation": "equals",
              "value2": "contacts"
            }
          ]
        }
      },
      "id": "if-contacts",
      "name": "IF Contacts",
      "type": "n8n-nodes-base.if",
      "typeVersion": 1,
      "position": [450, 300]
    },
    {
      "parameters": {
        "conditions": {
          "string": [
            {
              "value1": "={{ $json.query.endpoint }}",
              "operation": "equals",
              "value2": "contact360"
            }
          ]
        }
      },
      "id": "if-contact360",
      "name": "IF Contact360",
      "type": "n8n-nodes-base.if",
      "typeVersion": 1,
      "position": [450, 400]
    },
    {
      "parameters": {
        "conditions": {
          "string": [
            {
              "value1": "={{ $json.query.endpoint }}",
              "operation": "equals",
              "value2": "hot-leads"
            }
          ]
        }
      },
      "id": "if-hotleads",
      "name": "IF HotLeads",
      "type": "n8n-nodes-base.if",
      "typeVersion": 1,
      "position": [450, 500]
    },
    {
      "parameters": {
        "conditions": {
          "string": [
            {
              "value1": "={{ $json.query.endpoint }}",
              "operation": "equals",
              "value2": "follow-ups"
            }
          ]
        }
      },
      "id": "if-followups",
      "name": "IF FollowUps",
      "type": "n8n-nodes-base.if",
      "typeVersion": 1,
      "position": [450, 600]
    },
    {
      "parameters": {
        "workflowId": "={{ $env.WORKFLOW_ID_METRICS }}"
      },
      "id": "execute-metrics",
      "name": "Execute Metrics Workflow",
      "type": "n8n-nodes-base.executeWorkflow",
      "typeVersion": 1,
      "position": [650, 100]
    },
    {
      "parameters": {
        "workflowId": "={{ $env.WORKFLOW_ID_PIPELINE }}"
      },
      "id": "execute-pipeline",
      "name": "Execute Pipeline Workflow",
      "type": "n8n-nodes-base.executeWorkflow",
      "typeVersion": 1,
      "position": [650, 200]
    },
    {
      "parameters": {
        "workflowId": "={{ $env.WORKFLOW_ID_CONTACTS }}"
      },
      "id": "execute-contacts",
      "name": "Execute Contacts Workflow",
      "type": "n8n-nodes-base.executeWorkflow",
      "typeVersion": 1,
      "position": [650, 300]
    },
    {
      "parameters": {
        "workflowId": "={{ $env.WORKFLOW_ID_CONTACT360 }}"
      },
      "id": "execute-contact360",
      "name": "Execute Contact360 Workflow",
      "type": "n8n-nodes-base.executeWorkflow",
      "typeVersion": 1,
      "position": [650, 400]
    },
    {
      "parameters": {
        "workflowId": "={{ $env.WORKFLOW_ID_HOTLEADS }}"
      },
      "id": "execute-hotleads",
      "name": "Execute HotLeads Workflow",
      "type": "n8n-nodes-base.executeWorkflow",
      "typeVersion": 1,
      "position": [650, 500]
    },
    {
      "parameters": {
        "workflowId": "={{ $env.WORKFLOW_ID_FOLLOWUPS }}"
      },
      "id": "execute-followups",
      "name": "Execute FollowUps Workflow",
      "type": "n8n-nodes-base.executeWorkflow",
      "typeVersion": 1,
      "position": [650, 600]
    },
    {
      "parameters": {
        "respondWith": "allIncomingItems"
      },
      "id": "respond-webhook",
      "name": "Respond to Webhook",
      "type": "n8n-nodes-base.respondToWebhook",
      "typeVersion": 1,
      "position": [850, 350]
    }
  ],
  "connections": {
    "Webhook": {
      "main": [
        [
          {
            "node": "IF Metrics",
            "type": "main",
            "index": 0
          },
          {
            "node": "IF Pipeline",
            "type": "main",
            "index": 0
          },
          {
            "node": "IF Contacts",
            "type": "main",
            "index": 0
          },
          {
            "node": "IF Contact360",
            "type": "main",
            "index": 0
          },
          {
            "node": "IF HotLeads",
            "type": "main",
            "index": 0
          },
          {
            "node": "IF FollowUps",
            "type": "main",
            "index": 0
          }
        ]
      ]
    },
    "IF Metrics": {
      "main": [
        [
          {
            "node": "Execute Metrics Workflow",
            "type": "main",
            "index": 0
          }
        ]
      ]
    },
    "IF Pipeline": {
      "main": [
        [
          {
            "node": "Execute Pipeline Workflow",
            "type": "main",
            "index": 0
          }
        ]
      ]
    },
    "IF Contacts": {
      "main": [
        [
          {
            "node": "Execute Contacts Workflow",
            "type": "main",
            "index": 0
          }
        ]
      ]
    },
    "IF Contact360": {
      "main": [
        [
          {
            "node": "Execute Contact360 Workflow",
            "type": "main",
            "index": 0
          }
        ]
      ]
    },
    "IF HotLeads": {
      "main": [
        [
          {
            "node": "Execute HotLeads Workflow",
            "type": "main",
            "index": 0
          }
        ]
      ]
    },
    "IF FollowUps": {
      "main": [
        [
          {
            "node": "Execute FollowUps Workflow",
            "type": "main",
            "index": 0
          }
        ]
      ]
    },
    "Execute Metrics Workflow": {
      "main": [
        [
          {
            "node": "Respond to Webhook",
            "type": "main",
            "index": 0
          }
        ]
      ]
    },
    "Execute Pipeline Workflow": {
      "main": [
        [
          {
            "node": "Respond to Webhook",
            "type": "main",
            "index": 0
          }
        ]
      ]
    },
    "Execute Contacts Workflow": {
      "main": [
        [
          {
            "node": "Respond to Webhook",
            "type": "main",
            "index": 0
          }
        ]
      ]
    },
    "Execute Contact360 Workflow": {
      "main": [
        [
          {
            "node": "Respond to Webhook",
            "type": "main",
            "index": 0
          }
        ]
      ]
    },
    "Execute HotLeads Workflow": {
      "main": [
        [
          {
            "node": "Respond to Webhook",
            "type": "main",
            "index": 0
          }
        ]
      ]
    },
    "Execute FollowUps Workflow": {
      "main": [
        [
          {
            "node": "Respond to Webhook",
            "type": "main",
            "index": 0
          }
        ]
      ]
    }
  },
  "settings": {
    "executionOrder": "v1"
  },
  "staticData": null,
  "tags": []
}
